{
  "Version":"2012-10-17",
  "Statement":[
    {
      "Effect":"Allow",
      "Principal":{"Federated":"arn:aws:iam::876253813400:oidc-provider/token.actions.githubusercontent.com"},
      "Action":"sts:AssumeRoleWithWebIdentity",
      "Condition":{
        "StringEquals":{
          "token.actions.githubusercontent.com:aud":"sts.amazonaws.com",
          "token.actions.githubusercontent.com:sub":"repo:JuanAldairRamirezMendez/PAT-AH:ref:refs/heads/circleci-project-setup"
        }
      }
    }
  ]
}
